README.md
setup.py
pysolana/__init__.py
pysolana/api.py
pysolana/sol.py
pysolana.egg-info/PKG-INFO
pysolana.egg-info/SOURCES.txt
pysolana.egg-info/dependency_links.txt
pysolana.egg-info/top_level.txt