Metadata-Version: 2.1
Name: pysolana
Version: 0.1.6
Summary: Python Solana Package
Home-page: https://github.com/Gusarich/pysolana
Author: Sedov Daniel
Author-email: danielsedovzzz@gmail.com
License: UNKNOWN
Platform: UNKNOWN
Classifier: Programming Language :: Python :: 3
Classifier: License :: OSI Approved :: MIT License
Classifier: Operating System :: OS Independent
Requires-Python: >=3.6
